mutwo/zimmermann_generators/__init__.py
mutwo/zimmermann_generators/extended_chomsky.py
mutwo/zimmermann_generators/interlockings.py
mutwo.ext_zimmermann-0.3.6.dist-info/LICENSE
mutwo.ext_zimmermann-0.3.6.dist-info/METADATA
mutwo.ext_zimmermann-0.3.6.dist-info/WHEEL
mutwo.ext_zimmermann-0.3.6.dist-info/top_level.txt
mutwo.ext_zimmermann-0.3.6.dist-info/RECORD
