Metadata-Version: 2.1
Name: mutwo.ext-zimmermann
Version: 0.3.6
Summary: zimmermann extension for event based framework for generative art
Home-page: https://github.com/mutwo-org/mutwo.ext-zimmermann
Author: Levin Eric Zimmermann
Author-email: levin.eric.zimmermann@posteo.eu
License: GPL
Project-URL: Documentation, https://mutwo.readthedocs.io/en/latest/
Platform: UNKNOWN
Requires-Python: >=3.9, <4
License-File: LICENSE
Requires-Dist: mutwo.ext-core (<0.58.0,>=0.56.0)
Requires-Dist: mutwo.ext-music (<0.13.0,>=0.8.0)
Requires-Dist: mutwo.ext-common-generators (<1.0.0,>=0.8.0)
Provides-Extra: testing
Requires-Dist: nose ; extra == 'testing'
Requires-Dist: coveralls ; extra == 'testing'
